ShauryaWarrior_STT/__init__.py
ShauryaWarrior_STT-0.2.dist-info/METADATA
ShauryaWarrior_STT-0.2.dist-info/WHEEL
ShauryaWarrior_STT-0.2.dist-info/top_level.txt
ShauryaWarrior_STT-0.2.dist-info/RECORD
