Metadata-Version: 2.1
Name: ShauryaWarrior-STT
Version: 0.2
Summary: A Python package for Speech-to-Text conversion
Author: ShauryaWarrior
Author-email: minecraft1212121212121213@gmail.com
